<?xml version="1.0" encoding="UTF-8"?>
<quer:query productCode="OR1015" model="http://www.taleo.com/ws/or800/2009/01" projectedClass="EmployeeReview" locale="en" mode="CSV" csvheader="true" csvdelimiter="|" largegraph="true" preventDuplicates="false" xmlns:quer="http://www.taleo.com/ws/integration/query"><quer:subQueries/>

<quer:projections>
<quer:projection><quer:field path="Number"/></quer:projection>
<quer:projection><quer:field path="ReviewDefinition,Title,Name"/></quer:projection>
<quer:projection><quer:field path="StartDate"/></quer:projection>
<quer:projection><quer:field path="EndDate"/></quer:projection>
<quer:projection><quer:field path="Employee,TalentUser,ArUser,EmployeeID"/></quer:projection>
<quer:projection><quer:field path="Employee,TalentUser,ArUser,FirstName"/></quer:projection>
<quer:projection><quer:field path="Employee,TalentUser,ArUser,Initial"/></quer:projection>
<quer:projection><quer:field path="Employee,TalentUser,ArUser,LastName"/></quer:projection>
<quer:projection><quer:field path="Employee,TalentUser,ArUser,Title"/></quer:projection>
<quer:projection><quer:field path="ManagerReview,Status,Code"/></quer:projection>
<quer:projection><quer:field path="ReviewDefinition,Title,Name"/></quer:projection>
<quer:projection><quer:field path="ReviewDefinition,Code"/></quer:projection>
<quer:projection><quer:field path="Manager,TalentUser,ArUser,FirstName"/></quer:projection>
<quer:projection><quer:field path="Manager,TalentUser,ArUser,Initial"/></quer:projection>
<quer:projection><quer:field path="Manager,TalentUser,ArUser,LastName"/></quer:projection>
<quer:projection><quer:field path="Manager,TalentUser,ArUser,Title"/></quer:projection>

<quer:projection><quer:field path="ReviewDefinition,Instruction,DefaultContextualizedTextValue,ContextualizedTextValue"/></quer:projection>
<quer:projection><quer:field path="ReviewDefinition,SummaryInstruction,DefaultContextualizedTextValue,ContextualizedTextValue"/></quer:projection>
<quer:projection><quer:field path="ReviewDefinition,ReviewSections,Name"/></quer:projection>
<quer:projection><quer:field path="ReviewDefinition,ReviewSections,SectionInstruction,DefaultContextualizedTextValue,ContextualizedTextValue"/></quer:projection>
<quer:projection><quer:field path="ReviewDefinition,ReviewSections,ReviewItems,Name"/></quer:projection>
<quer:projection><quer:field path="ReviewDefinition,OverallEmployeeReviewEntry,Comment"/></quer:projection>
<quer:projection><quer:field path="ReviewDefinition,ReviewSections,ReviewItems,EmployeeReviewEntry,Comment"/></quer:projection>
<quer:projection><quer:field path="ReviewDefinition,ReviewSections,ReviewItems,SelfAssessmentEntry,Comment"/></quer:projection>

<quer:projection><quer:field path="ManagerReview,OverallScore,RatingValue,Name"/></quer:projection>
<quer:projection><quer:field path="ManagerReview,OverallScore,RatingValue,NumericValue"/></quer:projection>
<quer:projection><quer:field path="ManagerReview,OverallScore,Comment"/></quer:projection>
<quer:projection><quer:field path="ManagerReview,EmployeeGoalSectionEntry,ItemsEntries,EmployeeGoal,Name"/></quer:projection>
<quer:projection><quer:field path="ManagerReview,EmployeeGoalSectionEntry,RatingValue,Name"/></quer:projection>
<quer:projection><quer:field path="ManagerReview,EmployeeGoalSectionEntry,RatingValue,NumericValue"/></quer:projection>
<quer:projection><quer:field path="ManagerReview,EmployeeGoalSectionEntry,Weight"/></quer:projection>
<quer:projection><quer:field path="ManagerReview,EmployeeGoalSectionEntry,ItemsEntries,EmployeeGoal,Description"/></quer:projection>
<quer:projection><quer:field path="ManagerReview,SectionsEntries,Comment"/></quer:projection>
<quer:projection><quer:field path="ManagerReview,SectionsEntries,ItemsEntries,Competency,DescriptionText"/></quer:projection>
<quer:projection><quer:field path="ManagerReview,CompetencySectionEntry,RatingValue,Name"/></quer:projection>
<quer:projection><quer:field path="ManagerReview,CompetencySectionEntry,RatingValue,NumericValue"/></quer:projection>
<quer:projection><quer:field path="ManagerReview,CompetencySectionEntry,Comment"/></quer:projection>
<quer:projection><quer:field path="ManagerReview,FinalComment"/></quer:projection>
<quer:projection><quer:field path="ManagerReview,EmployeeGoalSectionEntry,ItemsEntries,EmployeeGoal,InitialValue"/></quer:projection>
<quer:projection><quer:field path="ManagerReview,EmployeeGoalSectionEntry,ItemsEntries,EmployeeGoal,ActualValue"/></quer:projection>
<quer:projection><quer:field path="ManagerReview,EmployeeGoalSectionEntry,ItemsEntries,EmployeeGoal,TargetValue"/></quer:projection>
<quer:projection><quer:field path="ManagerReview,AcknowledgementComment"/></quer:projection>
<quer:projection><quer:field path="ManagerReview,ReviewMeetingComment"/></quer:projection>
<quer:projection><quer:field path="ManagerReview,HistoryComment"/></quer:projection>

<quer:projection><quer:field path="SelfReview,OverallScore,RatingValue,Name"/></quer:projection>
<quer:projection><quer:field path="SelfReview,OverallScore,RatingValue,NumericValue"/></quer:projection>
<quer:projection><quer:field path="SelfReview,OverallScore,Comment"/></quer:projection>
<quer:projection><quer:field path="SelfReview,EmployeeGoalSectionEntry,Comment"/></quer:projection>
<quer:projection><quer:field path="SelfReview,EmployeeGoalSectionEntry,RatingValue,Name"/></quer:projection>
<quer:projection><quer:field path="SelfReview,EmployeeGoalSectionEntry,RatingValue,NumericValue"/></quer:projection>
<quer:projection><quer:field path="SelfReview,EmployeeGoalSectionEntry,Weight"/></quer:projection>
<quer:projection><quer:field path="SelfReview,CompetencySectionEntry,Comment"/></quer:projection>
<quer:projection><quer:field path="SelfReview,AcknowledgementComment"/></quer:projection>
<quer:projection><quer:field path="SelfReview,ReviewMeetingComment"/></quer:projection>
<quer:projection><quer:field path="SelfReview,HistoryComment"/></quer:projection>


<quer:projection alias="MgrRevCreationDate" projectedValueType="string">
<quer:customFunction name="TO_CHAR"><quer:field path="ManagerReview,CreationDate"/>
<quer:string>yyyy-MM-dd</quer:string>
</quer:customFunction>
</quer:projection><quer:projection alias="MgrRevApprovedDate" projectedValueType="string">
<quer:customFunction name="TO_CHAR"><quer:field path="ManagerReview,ApprovedDate"/>
<quer:string>yyyy-MM-dd</quer:string>
</quer:customFunction>
</quer:projection><quer:projection alias="MgrRevReleasedDate" projectedValueType="string">
<quer:customFunction name="TO_CHAR"><quer:field path="ManagerReview,ReleasedDate"/>
<quer:string>yyyy-MM-dd</quer:string>
</quer:customFunction>
</quer:projection><quer:projection alias="MgrRevAcknowledgementReqdDate" projectedValueType="string">
<quer:customFunction name="TO_CHAR"><quer:field path="ManagerReview,AcknowledgementRequestedDate"/>
<quer:string>yyyy-MM-dd</quer:string>
</quer:customFunction>
</quer:projection><quer:projection alias="MgrRevAcknowledgedDate" projectedValueType="string">
<quer:customFunction name="TO_CHAR"><quer:field path="ManagerReview,AcknowledgedDate"/>
<quer:string>yyyy-MM-dd</quer:string>
</quer:customFunction>
</quer:projection><quer:projection alias="MgrRevReviewMeetingDate" projectedValueType="string">
<quer:customFunction name="TO_CHAR"><quer:field path="ManagerReview,ReviewMeetingDate"/>
<quer:string>yyyy-MM-dd</quer:string>
</quer:customFunction>
</quer:projection><quer:projection alias="MgrRevCalibratedDate" projectedValueType="string">
<quer:customFunction name="TO_CHAR"><quer:field path="ManagerReview,CalibratedDate"/>
<quer:string>yyyy-MM-dd</quer:string>
</quer:customFunction>
</quer:projection><quer:projection alias="MgrRevClosedDate" projectedValueType="string">
<quer:customFunction name="TO_CHAR"><quer:field path="ManagerReview,ClosedDate"/>
<quer:string>yyyy-MM-dd</quer:string>
</quer:customFunction>
</quer:projection><quer:projection alias="EmpRevCreationDate" projectedValueType="string">
<quer:customFunction name="TO_CHAR"><quer:field path="SelfReview,CreationDate"/>
<quer:string>yyyy-MM-dd</quer:string>
</quer:customFunction>
</quer:projection><quer:projection alias="EmpRevApprovedDate" projectedValueType="string">
<quer:customFunction name="TO_CHAR"><quer:field path="SelfReview,ApprovedDate"/>
<quer:string>yyyy-MM-dd</quer:string>
</quer:customFunction>
</quer:projection><quer:projection alias="EmpRevReleasedDate" projectedValueType="string">
<quer:customFunction name="TO_CHAR"><quer:field path="SelfReview,ReleasedDate"/>
<quer:string>yyyy-MM-dd</quer:string>
</quer:customFunction>
</quer:projection><quer:projection alias="EmpRevAcknowledgementReqDate" projectedValueType="string">
<quer:customFunction name="TO_CHAR"><quer:field path="SelfReview,AcknowledgementRequestedDate"/>
<quer:string>yyyy-MM-dd</quer:string>
</quer:customFunction>
</quer:projection><quer:projection alias="EmpRevAcknowledgedDate" projectedValueType="string">
<quer:customFunction name="TO_CHAR"><quer:field path="SelfReview,AcknowledgedDate"/>
<quer:string>yyyy-MM-dd</quer:string>
</quer:customFunction>
</quer:projection><quer:projection alias="EmpRevReviewMeetingDate" projectedValueType="string">
<quer:customFunction name="TO_CHAR"><quer:field path="SelfReview,ReviewMeetingDate"/>
<quer:string>yyyy-MM-dd</quer:string>
</quer:customFunction>
</quer:projection><quer:projection alias="EmpRevCalibratedDate" projectedValueType="string">
<quer:customFunction name="TO_CHAR"><quer:field path="SelfReview,CalibratedDate"/>
<quer:string>yyyy-MM-dd</quer:string>
</quer:customFunction>
</quer:projection><quer:projection alias="EmpRevClosedDate" projectedValueType="string">
<quer:customFunction name="TO_CHAR"><quer:field path="SelfReview,ClosedDate"/>
<quer:string>yyyy-MM-dd</quer:string>
</quer:customFunction>
</quer:projection>
</quer:projections>

<quer:projectionFilterings/>
<quer:filterings>
<quer:filtering><quer:greaterThanOrEqual><quer:field path="StartDate"/><quer:date>2014-01-01</quer:date></quer:greaterThanOrEqual></quer:filtering>
<quer:filtering><quer:lessThanOrEqual><quer:field path="EndDate"/><quer:date>2014-12-31</quer:date></quer:lessThanOrEqual></quer:filtering>
<!-- <quer:filtering><quer:equal><quer:field path="ReviewDefinition,Code"/><quer:string>2017_FedEx_Supply_Chain_Annual_Leader</quer:string></quer:equal></quer:filtering> -->

<quer:filtering>
  <quer:includedIn>
    <quer:field path="Number"/>
    <quer:list>

<quer:string>23875</quer:string> 
<quer:string>23876</quer:string> 
<quer:string>23877</quer:string> 
<quer:string>23878</quer:string> 
<quer:string>23879</quer:string> 
<quer:string>23880</quer:string> 
<quer:string>23881</quer:string> 
<quer:string>23882</quer:string> 
<quer:string>23883</quer:string> 
<quer:string>23884</quer:string> 
<quer:string>23885</quer:string> 
<quer:string>23886</quer:string> 
<quer:string>23887</quer:string> 
<quer:string>23888</quer:string> 
<quer:string>23889</quer:string> 
<quer:string>23890</quer:string> 
<quer:string>23891</quer:string> 
<quer:string>23892</quer:string> 
<quer:string>23893</quer:string> 
<quer:string>23894</quer:string> 
<quer:string>23895</quer:string> 
<quer:string>23896</quer:string> 
<quer:string>23897</quer:string> 
<quer:string>23898</quer:string> 
<quer:string>23899</quer:string> 
<quer:string>23900</quer:string> 
<quer:string>23901</quer:string> 
<quer:string>23902</quer:string> 
<quer:string>23903</quer:string> 
<quer:string>23904</quer:string> 
<quer:string>23905</quer:string> 
<quer:string>23906</quer:string> 
<quer:string>23907</quer:string> 
<quer:string>23908</quer:string> 
<quer:string>23909</quer:string> 
<quer:string>23910</quer:string> 
<quer:string>23911</quer:string> 
<quer:string>23912</quer:string> 
<quer:string>23913</quer:string> 
<quer:string>23914</quer:string> 
<quer:string>24393</quer:string> 
<quer:string>24394</quer:string> 
<quer:string>24399</quer:string> 
<quer:string>24400</quer:string> 
<quer:string>24401</quer:string> 
<quer:string>24402</quer:string> 
<quer:string>24403</quer:string> 
<quer:string>24404</quer:string> 
<quer:string>24408</quer:string> 
<quer:string>24409</quer:string> 
<quer:string>24416</quer:string> 
<quer:string>24418</quer:string> 
<quer:string>24419</quer:string> 
<quer:string>24420</quer:string> 
<quer:string>24423</quer:string> 
<quer:string>24425</quer:string> 
<quer:string>24426</quer:string> 
<quer:string>24427</quer:string> 
<quer:string>24438</quer:string> 
<quer:string>24439</quer:string> 
<quer:string>24440</quer:string> 
<quer:string>24441</quer:string> 
<quer:string>24442</quer:string> 
<quer:string>24446</quer:string> 
<quer:string>24447</quer:string> 
<quer:string>24449</quer:string> 
<quer:string>24450</quer:string> 
<quer:string>24451</quer:string> 
<quer:string>24452</quer:string> 
<quer:string>24453</quer:string> 
<quer:string>24454</quer:string> 
<quer:string>24455</quer:string> 
<quer:string>24457</quer:string> 
<quer:string>24458</quer:string> 
<quer:string>24460</quer:string> 
<quer:string>24465</quer:string> 
<quer:string>24468</quer:string> 
<quer:string>24475</quer:string> 
<quer:string>24476</quer:string> 
<quer:string>24477</quer:string> 
<quer:string>24478</quer:string> 
<quer:string>24480</quer:string> 
<quer:string>24481</quer:string> 
<quer:string>24482</quer:string> 
<quer:string>24483</quer:string> 
<quer:string>24484</quer:string> 
<quer:string>24486</quer:string> 
<quer:string>24487</quer:string> 
<quer:string>24488</quer:string> 
<quer:string>24489</quer:string> 
<quer:string>24490</quer:string> 
<quer:string>24491</quer:string> 
<quer:string>24492</quer:string> 
<quer:string>24495</quer:string> 
<quer:string>24499</quer:string> 
<quer:string>24500</quer:string> 
<quer:string>24501</quer:string> 
<quer:string>24521</quer:string> 
<quer:string>24522</quer:string> 
<quer:string>24523</quer:string> 
<quer:string>24525</quer:string> 
<quer:string>24539</quer:string> 
<quer:string>24559</quer:string> 
<quer:string>24560</quer:string> 

	
    </quer:list>
  </quer:includedIn>
</quer:filtering>

</quer:filterings>

<quer:sortings><quer:sorting ascending="true"><quer:field path="Number"/></quer:sorting></quer:sortings><quer:sortingFilterings/><quer:groupings/><quer:joinings/></quer:query>