<?xml version="1.0" encoding="UTF-8"?>
<quer:query productCode="OR1015" model="http://www.taleo.com/ws/or800/2009/01" projectedClass="EmployeeReview" locale="en" mode="CSV" csvheader="true" csvdelimiter="|" largegraph="true" preventDuplicates="false" xmlns:quer="http://www.taleo.com/ws/integration/query"><quer:subQueries/>

<quer:projections>
<quer:projection><quer:field path="Number"/></quer:projection>
<quer:projection><quer:field path="ReviewDefinition,Title,Name"/></quer:projection>
<quer:projection><quer:field path="StartDate"/></quer:projection>
<quer:projection><quer:field path="EndDate"/></quer:projection>
<quer:projection><quer:field path="Employee,TalentUser,ArUser,EmployeeID"/></quer:projection>
<quer:projection><quer:field path="Employee,TalentUser,ArUser,FirstName"/></quer:projection>
<quer:projection><quer:field path="Employee,TalentUser,ArUser,Initial"/></quer:projection>
<quer:projection><quer:field path="Employee,TalentUser,ArUser,LastName"/></quer:projection>
<quer:projection><quer:field path="Employee,TalentUser,ArUser,Title"/></quer:projection>
<quer:projection><quer:field path="ManagerReview,Status,Code"/></quer:projection>
<quer:projection><quer:field path="ReviewDefinition,Title,Name"/></quer:projection>
<quer:projection><quer:field path="ReviewDefinition,Code"/></quer:projection>
<quer:projection><quer:field path="Manager,TalentUser,ArUser,FirstName"/></quer:projection>
<quer:projection><quer:field path="Manager,TalentUser,ArUser,Initial"/></quer:projection>
<quer:projection><quer:field path="Manager,TalentUser,ArUser,LastName"/></quer:projection>
<quer:projection><quer:field path="Manager,TalentUser,ArUser,Title"/></quer:projection>

<quer:projection><quer:field path="ReviewDefinition,Instruction,DefaultContextualizedTextValue,ContextualizedTextValue"/></quer:projection>
<quer:projection><quer:field path="ReviewDefinition,SummaryInstruction,DefaultContextualizedTextValue,ContextualizedTextValue"/></quer:projection>
<quer:projection><quer:field path="ReviewDefinition,ReviewSections,Name"/></quer:projection>
<quer:projection><quer:field path="ReviewDefinition,ReviewSections,SectionInstruction,DefaultContextualizedTextValue,ContextualizedTextValue"/></quer:projection>
<quer:projection><quer:field path="ReviewDefinition,ReviewSections,ReviewItems,Name"/></quer:projection>
<quer:projection><quer:field path="ReviewDefinition,OverallEmployeeReviewEntry,Comment"/></quer:projection>
<quer:projection><quer:field path="ReviewDefinition,ReviewSections,ReviewItems,EmployeeReviewEntry,Comment"/></quer:projection>
<quer:projection><quer:field path="ReviewDefinition,ReviewSections,ReviewItems,SelfAssessmentEntry,Comment"/></quer:projection>

<quer:projection><quer:field path="ManagerReview,OverallScore,RatingValue,Name"/></quer:projection>
<quer:projection><quer:field path="ManagerReview,OverallScore,RatingValue,NumericValue"/></quer:projection>
<quer:projection><quer:field path="ManagerReview,OverallScore,Comment"/></quer:projection>
<quer:projection><quer:field path="ManagerReview,EmployeeGoalSectionEntry,ItemsEntries,EmployeeGoal,Name"/></quer:projection>
<quer:projection><quer:field path="ManagerReview,EmployeeGoalSectionEntry,RatingValue,Name"/></quer:projection>
<quer:projection><quer:field path="ManagerReview,EmployeeGoalSectionEntry,RatingValue,NumericValue"/></quer:projection>
<quer:projection><quer:field path="ManagerReview,EmployeeGoalSectionEntry,Weight"/></quer:projection>
<quer:projection><quer:field path="ManagerReview,EmployeeGoalSectionEntry,ItemsEntries,EmployeeGoal,Description"/></quer:projection>
<quer:projection><quer:field path="ManagerReview,SectionsEntries,Comment"/></quer:projection>
<quer:projection><quer:field path="ManagerReview,SectionsEntries,ItemsEntries,Competency,DescriptionText"/></quer:projection>
<quer:projection><quer:field path="ManagerReview,CompetencySectionEntry,RatingValue,Name"/></quer:projection>
<quer:projection><quer:field path="ManagerReview,CompetencySectionEntry,RatingValue,NumericValue"/></quer:projection>
<quer:projection><quer:field path="ManagerReview,CompetencySectionEntry,Comment"/></quer:projection>
<quer:projection><quer:field path="ManagerReview,FinalComment"/></quer:projection>
<quer:projection><quer:field path="ManagerReview,EmployeeGoalSectionEntry,ItemsEntries,EmployeeGoal,InitialValue"/></quer:projection>
<quer:projection><quer:field path="ManagerReview,EmployeeGoalSectionEntry,ItemsEntries,EmployeeGoal,ActualValue"/></quer:projection>
<quer:projection><quer:field path="ManagerReview,EmployeeGoalSectionEntry,ItemsEntries,EmployeeGoal,TargetValue"/></quer:projection>
<quer:projection><quer:field path="ManagerReview,AcknowledgementComment"/></quer:projection>
<quer:projection><quer:field path="ManagerReview,ReviewMeetingComment"/></quer:projection>
<quer:projection><quer:field path="ManagerReview,HistoryComment"/></quer:projection>

<quer:projection><quer:field path="SelfReview,OverallScore,RatingValue,Name"/></quer:projection>
<quer:projection><quer:field path="SelfReview,OverallScore,RatingValue,NumericValue"/></quer:projection>
<quer:projection><quer:field path="SelfReview,OverallScore,Comment"/></quer:projection>
<quer:projection><quer:field path="SelfReview,EmployeeGoalSectionEntry,Comment"/></quer:projection>
<quer:projection><quer:field path="SelfReview,EmployeeGoalSectionEntry,RatingValue,Name"/></quer:projection>
<quer:projection><quer:field path="SelfReview,EmployeeGoalSectionEntry,RatingValue,NumericValue"/></quer:projection>
<quer:projection><quer:field path="SelfReview,EmployeeGoalSectionEntry,Weight"/></quer:projection>
<quer:projection><quer:field path="SelfReview,CompetencySectionEntry,Comment"/></quer:projection>
<quer:projection><quer:field path="SelfReview,AcknowledgementComment"/></quer:projection>
<quer:projection><quer:field path="SelfReview,ReviewMeetingComment"/></quer:projection>
<quer:projection><quer:field path="SelfReview,HistoryComment"/></quer:projection>


<quer:projection alias="MgrRevCreationDate" projectedValueType="string">
<quer:customFunction name="TO_CHAR"><quer:field path="ManagerReview,CreationDate"/>
<quer:string>yyyy-MM-dd</quer:string>
</quer:customFunction>
</quer:projection><quer:projection alias="MgrRevApprovedDate" projectedValueType="string">
<quer:customFunction name="TO_CHAR"><quer:field path="ManagerReview,ApprovedDate"/>
<quer:string>yyyy-MM-dd</quer:string>
</quer:customFunction>
</quer:projection><quer:projection alias="MgrRevReleasedDate" projectedValueType="string">
<quer:customFunction name="TO_CHAR"><quer:field path="ManagerReview,ReleasedDate"/>
<quer:string>yyyy-MM-dd</quer:string>
</quer:customFunction>
</quer:projection><quer:projection alias="MgrRevAcknowledgementReqdDate" projectedValueType="string">
<quer:customFunction name="TO_CHAR"><quer:field path="ManagerReview,AcknowledgementRequestedDate"/>
<quer:string>yyyy-MM-dd</quer:string>
</quer:customFunction>
</quer:projection><quer:projection alias="MgrRevAcknowledgedDate" projectedValueType="string">
<quer:customFunction name="TO_CHAR"><quer:field path="ManagerReview,AcknowledgedDate"/>
<quer:string>yyyy-MM-dd</quer:string>
</quer:customFunction>
</quer:projection><quer:projection alias="MgrRevReviewMeetingDate" projectedValueType="string">
<quer:customFunction name="TO_CHAR"><quer:field path="ManagerReview,ReviewMeetingDate"/>
<quer:string>yyyy-MM-dd</quer:string>
</quer:customFunction>
</quer:projection><quer:projection alias="MgrRevCalibratedDate" projectedValueType="string">
<quer:customFunction name="TO_CHAR"><quer:field path="ManagerReview,CalibratedDate"/>
<quer:string>yyyy-MM-dd</quer:string>
</quer:customFunction>
</quer:projection><quer:projection alias="MgrRevClosedDate" projectedValueType="string">
<quer:customFunction name="TO_CHAR"><quer:field path="ManagerReview,ClosedDate"/>
<quer:string>yyyy-MM-dd</quer:string>
</quer:customFunction>
</quer:projection><quer:projection alias="EmpRevCreationDate" projectedValueType="string">
<quer:customFunction name="TO_CHAR"><quer:field path="SelfReview,CreationDate"/>
<quer:string>yyyy-MM-dd</quer:string>
</quer:customFunction>
</quer:projection><quer:projection alias="EmpRevApprovedDate" projectedValueType="string">
<quer:customFunction name="TO_CHAR"><quer:field path="SelfReview,ApprovedDate"/>
<quer:string>yyyy-MM-dd</quer:string>
</quer:customFunction>
</quer:projection><quer:projection alias="EmpRevReleasedDate" projectedValueType="string">
<quer:customFunction name="TO_CHAR"><quer:field path="SelfReview,ReleasedDate"/>
<quer:string>yyyy-MM-dd</quer:string>
</quer:customFunction>
</quer:projection><quer:projection alias="EmpRevAcknowledgementReqDate" projectedValueType="string">
<quer:customFunction name="TO_CHAR"><quer:field path="SelfReview,AcknowledgementRequestedDate"/>
<quer:string>yyyy-MM-dd</quer:string>
</quer:customFunction>
</quer:projection><quer:projection alias="EmpRevAcknowledgedDate" projectedValueType="string">
<quer:customFunction name="TO_CHAR"><quer:field path="SelfReview,AcknowledgedDate"/>
<quer:string>yyyy-MM-dd</quer:string>
</quer:customFunction>
</quer:projection><quer:projection alias="EmpRevReviewMeetingDate" projectedValueType="string">
<quer:customFunction name="TO_CHAR"><quer:field path="SelfReview,ReviewMeetingDate"/>
<quer:string>yyyy-MM-dd</quer:string>
</quer:customFunction>
</quer:projection><quer:projection alias="EmpRevCalibratedDate" projectedValueType="string">
<quer:customFunction name="TO_CHAR"><quer:field path="SelfReview,CalibratedDate"/>
<quer:string>yyyy-MM-dd</quer:string>
</quer:customFunction>
</quer:projection><quer:projection alias="EmpRevClosedDate" projectedValueType="string">
<quer:customFunction name="TO_CHAR"><quer:field path="SelfReview,ClosedDate"/>
<quer:string>yyyy-MM-dd</quer:string>
</quer:customFunction>
</quer:projection>
</quer:projections>

<quer:projectionFilterings/>
<quer:filterings>
<quer:filtering><quer:greaterThanOrEqual><quer:field path="StartDate"/><quer:date>2014-01-01</quer:date></quer:greaterThanOrEqual></quer:filtering>
<quer:filtering><quer:lessThanOrEqual><quer:field path="EndDate"/><quer:date>2014-12-31</quer:date></quer:lessThanOrEqual></quer:filtering>
<!-- <quer:filtering><quer:equal><quer:field path="ReviewDefinition,Code"/><quer:string>2017_FedEx_Supply_Chain_Annual_Leader</quer:string></quer:equal></quer:filtering> -->

<quer:filtering>
  <quer:includedIn>
    <quer:field path="Number"/>
    <quer:list>

<quer:string>20129</quer:string> 
<quer:string>20130</quer:string> 
<quer:string>20131</quer:string> 
<quer:string>20132</quer:string> 
<quer:string>20133</quer:string> 
<quer:string>20134</quer:string> 
<quer:string>20135</quer:string> 
<quer:string>20136</quer:string> 
<quer:string>20137</quer:string> 
<quer:string>20138</quer:string> 
<quer:string>20179</quer:string> 
<quer:string>20180</quer:string> 
<quer:string>20181</quer:string> 
<quer:string>20182</quer:string> 
<quer:string>20183</quer:string> 
<quer:string>20184</quer:string> 
<quer:string>20185</quer:string> 
<quer:string>20186</quer:string> 
<quer:string>20187</quer:string> 
<quer:string>20188</quer:string> 
<quer:string>20189</quer:string> 
<quer:string>20190</quer:string> 
<quer:string>20191</quer:string> 
<quer:string>20192</quer:string> 
<quer:string>20193</quer:string> 
<quer:string>20194</quer:string> 
<quer:string>20195</quer:string> 
<quer:string>20196</quer:string> 
<quer:string>20197</quer:string> 
<quer:string>20198</quer:string> 
<quer:string>20219</quer:string> 
<quer:string>20220</quer:string> 
<quer:string>20221</quer:string> 
<quer:string>20222</quer:string> 
<quer:string>20223</quer:string> 
<quer:string>20224</quer:string> 
<quer:string>20225</quer:string> 
<quer:string>20226</quer:string> 
<quer:string>20227</quer:string> 
<quer:string>20228</quer:string> 
<quer:string>20229</quer:string> 
<quer:string>20230</quer:string> 
<quer:string>20231</quer:string> 
<quer:string>20232</quer:string> 
<quer:string>20233</quer:string> 
<quer:string>20234</quer:string> 
<quer:string>20235</quer:string> 
<quer:string>20236</quer:string> 
<quer:string>20237</quer:string> 
<quer:string>20238</quer:string> 
<quer:string>20239</quer:string> 
<quer:string>20240</quer:string> 
<quer:string>20241</quer:string> 
<quer:string>20242</quer:string> 
<quer:string>20243</quer:string> 
<quer:string>20244</quer:string> 
<quer:string>20245</quer:string> 
<quer:string>20246</quer:string> 
<quer:string>20247</quer:string> 
<quer:string>20248</quer:string> 
<quer:string>20249</quer:string> 
<quer:string>20250</quer:string> 
<quer:string>20251</quer:string> 
<quer:string>20252</quer:string> 
<quer:string>20253</quer:string> 
<quer:string>20254</quer:string> 
<quer:string>20255</quer:string> 
<quer:string>20256</quer:string> 
<quer:string>20257</quer:string> 
<quer:string>20258</quer:string> 
<quer:string>20259</quer:string> 
<quer:string>20260</quer:string> 
<quer:string>20261</quer:string> 
<quer:string>20262</quer:string> 
<quer:string>20263</quer:string> 
<quer:string>20264</quer:string> 
<quer:string>20265</quer:string> 
<quer:string>20266</quer:string> 
<quer:string>20267</quer:string> 
<quer:string>20268</quer:string> 
<quer:string>20269</quer:string> 
<quer:string>20270</quer:string> 
<quer:string>20271</quer:string> 
<quer:string>20272</quer:string> 
<quer:string>20273</quer:string> 
<quer:string>20210</quer:string> 
<quer:string>20211</quer:string> 
<quer:string>20212</quer:string> 
<quer:string>20213</quer:string> 
<quer:string>20214</quer:string> 
<quer:string>20215</quer:string> 
<quer:string>20216</quer:string> 
<quer:string>20217</quer:string> 
<quer:string>20218</quer:string> 
<quer:string>20379</quer:string> 
<quer:string>20380</quer:string> 
<quer:string>20381</quer:string> 
<quer:string>20382</quer:string> 
<quer:string>20383</quer:string> 
<quer:string>20384</quer:string> 
<quer:string>20385</quer:string> 
<quer:string>20386</quer:string> 
<quer:string>20387</quer:string> 
<quer:string>20388</quer:string> 

	
    </quer:list>
  </quer:includedIn>
</quer:filtering>

</quer:filterings>

<quer:sortings><quer:sorting ascending="true"><quer:field path="Number"/></quer:sorting></quer:sortings><quer:sortingFilterings/><quer:groupings/><quer:joinings/></quer:query>